{
  "name": "Stripe store",
  "slug": "stripe-store-plugin",
  "version": "1.0.0",
  "author": "Studio CMS",
  "description": "Stripe Checkout for purchasable content entries (e.g. products). No core code changes — enable the plugin, run its SQL migration, add a Stripe Price field, and include one script tag on product pages.",
  "requires_cms_version": "1.0.0",
  "requires_php": "8.1",
  "homepage": "",
  "repository_url": "",
  "license": "MIT",
  "category": "commerce",
  "tags": ["stripe", "payments", "checkout", "products"],
  "tested_up_to": "1.0.0",
  "main_class": "StripeStorePlugin\\StripeStorePluginServiceProvider",
  "enabled_by_default": false,
  "autoload": {
    "psr4": {
      "StripeStorePlugin\\": "src/"
    }
  }
}
